bandit_markdown/__init__.py
bandit_markdown/main.py
bandit_markdown-0.1.0.dist-info/entry_points.txt
bandit_markdown-0.1.0.dist-info/WHEEL
bandit_markdown-0.1.0.dist-info/METADATA
bandit_markdown-0.1.0.dist-info/RECORD
