Metadata-Version: 2.1
Name: bandit-markdown
Version: 0.1.0
Summary: 
Home-page: https://github.com/baniasbaabe/bandit-markdown
License: MIT
Keywords: bandit,markdown,security
Author: baniasbaabe
Author-email: banias@hotmail.de
Requires-Python: >=3.8,<4.0
Classifier: Environment :: Console
Classifier: Framework :: Flake8
Classifier: License :: OSI Approved :: MIT License
Classifier: Operating System :: OS Independent
Classifier: Programming Language :: Python :: 3
Classifier: Programming Language :: Python :: 3.10
Classifier: Programming Language :: Python :: 3.8
Classifier: Programming Language :: Python :: 3.9
Classifier: Topic :: Security
Classifier: Topic :: Software Development :: Documentation
Classifier: Topic :: Software Development :: Libraries :: Python Modules
Classifier: Topic :: Software Development :: Quality Assurance
Requires-Dist: bandit (>=1.7.5,<2.0.0)
Project-URL: Repository, https://github.com/baniasbaabe/bandit-markdown
